delvis/__init__.py
delvis/verify.py
delvis/constraints/__init__.py
delvis/constraints/base.py
delvis/engine/__init__.py
delvis/engine/frontier.py
delvis/engine/trie.py
delvis/engine/verifier.py
delvis/models/__init__.py
delvis/models/base.py
delvis/plugins/__init__.py
delvis/plugins/base.py
delvis/profiles/__init__.py
delvis/profiles/safety.py
delvis-0.0.1.dist-info/METADATA
delvis-0.0.1.dist-info/WHEEL
delvis-0.0.1.dist-info/RECORD
