Metadata-Version: 2.4
Name: delvis
Version: 0.0.1
Summary: DeLViS
Author-email: Dheeraj Bhat <dheerajnbhat@gmail.com>
Maintainer-email: Dheeraj Bhat <dheerajnbhat@gmail.com>
Keywords: delvis
Classifier: Intended Audience :: Developers
Classifier: Intended Audience :: Science/Research
Classifier: Programming Language :: Python :: 3 :: Only
Requires-Python: >=3.10
